Workbook

Sheet Opción Chino (1)
P2: Año 0 | Q2: Año 1 | R2: Año 2 | S2: Año 3 | T2: Año 4 | U2: Año 5
E3: Años | G3: Monto de | I3: Factor de | K3: Valor Actual | O3: Flujos de Operación
E4: Flujo de Caja | G4: Flujo de Caja | I4: Descuento | K4: Flujo de Caja
I5: al 8% | O5: Costos de Mantención | Q5: -100 | R5: =+Q5 -> -100 | S5: =+R5 -> -100 | T5: =+S5 -> -100 | U5: =+T5 -> -100 | W5: 1 | X5: puntos | Z5: =-P20 -> 2000 | AA5: =+'Opción Corea (2)'!AB6 -> Inversión
B6: ( 1- 15% ) | C6: 100 * 85% | O6: Depreciación | Q6: =(P20*0.9)/10 -> -180 | R6: =+Q6 -> -180 | S6: =+R6 -> -180 | T6: =+S6 -> -180 | U6: =+T6 -> -180 | W6: 1 | X6: puntos | Z6: =SUM(Q6:U6) -> -900 | AA6: =+'Opción Corea (2)'!AB7 -> Dep Ac
O7: Utilidad por Venta Bus | U7: 200 | W7: 1 | X7: puntos | Z7: =+Z5+Z6 -> 1100 | AA7: =+'Opción Corea (2)'!AB8 -> Valor libro
C8: =-100*0.85 -> -85 | E8: del año 1 al 5 | G8: =+C8 -> -85 | I8: 3.99271 | K8: =+I8*G8 -> -339.38035 | Z8: 1300 | AA8: =+'Opción Corea (2)'!AB9 -> Valor Venta
O9: UAI | Q9: =SUM(Q5:Q7) -> -280 | R9: =SUM(R5:R7) -> -280 | S9: =SUM(S5:S7) -> -280 | T9: =SUM(T5:T7) -> -280 | U9: =SUM(U5:U7) -> -80 | W9: 2 | X9: =+X7 -> puntos | Z9: =+Z8-Z7 -> 200 | AA9: Ut por Venta
B10: Total Costo Operación Variable despues de Impuestos | K10: =SUM(K8:K9) -> -339.38035 | M10: 3 | O10: Impuestos | Q10: =+Q9*0.15 -> -42 | R10: =+R9*0.15 -> -42 | S10: =+S9*0.15 -> -42 | T10: =+T9*0.15 -> -42 | U10: =+U9*0.15 -> -12 | W10: 2 | X10: =+X9 -> puntos
O11: Ut Neta | Q11: =+Q9-Q10 -> -238 | R11: =+R9-R10 -> -238 | S11: =+S9-S10 -> -238 | T11: =+T9-T10 -> -238 | U11: =+U9-U10 -> -68 | W11: 2 | X11: =+X9 -> puntos
O13: Depreciación | Q13: =+Q6 -> -180 | R13: =+R6 -> -180 | S13: =+S6 -> -180 | T13: =+T6 -> -180 | U13: =+U6 -> -180
B14: 3.- Deducciones por Depreciación | C14: 180 | O14: =+O7 -> Utilidad por Venta Bus | Q14: =+Q7 -> 0 | R14: =+R7 -> 0 | S14: =+S7 -> 0 | T14: =+T7 -> 0 | U14: =+U7 -> 200
B15: 0.15 | C15: * 15%
B16: Ahorro de Impuestos por Depreciación | C16: =C14*0.15 -> 27 | E16: del año 1 al 5 | G16: =C16 -> 27 | I16: =+I8 -> 3.99271 | K16: =G16*I16 -> 107.80317 | M16: 3 | O16: Flujo Operativo | Q16: =+Q11-Q13-Q14 -> -58 | R16: =+R11-R13-R14 -> -58 | S16: =+S11-S13-S14 -> -58 | T16: =+T11-T13-T14 -> -58 | U16: =+U11-U13-U14 -> -88 | W16: 4 | X16: =+X11 -> puntos
B18: 4.- Valor de Rescate Red Actual | C18: 1300 | O18: Flujos de Inversión
B19: ( 1- 15% )
B20: Ingreso Neto de Caja | C20: =+C18 -> 1300 | E20: al año 5 | G20: =C20 -> 1300 | I20: =1/(1.08^5) -> 0.6805832 | K20: =I20*G20 -> 884.75816 | M20: 3 | O20: Inversión Bus | P20: -2000 | W20: 1 | X20: puntos
O21: Venta Bus | U21: 1300 | W21: 1 | X21: punto
B22: Utilidad por Venta Máquina | C22: 200
C23: =-C22*0.15 -> -30 | E23: al año 5 | G23: =+C23 -> -30 | I23: =+I20 -> 0.6805832 | K23: =I23*G23 -> -20.417496 | M23: 3 | O23: Flujo Inversión | P23: =+P20 -> -2000 | U23: =+U20+U21 -> 1300
O25: Flujo Total | P25: =+P16+P23 -> -2000 | Q25: =+Q16+Q23 -> -58 | R25: =+R16+R23 -> -58 | S25: =+S16+S23 -> -58 | T25: =+T16+T23 -> -58 | U25: =+U16+U23 -> 1212
O27: VP | P27: =+P25 -> -2000 | Q27: =+Q25/(1.08^1) -> -53.703704 | R27: =+R25/(1.08^2) -> -49.725652 | S27: =+S25/(1.08^3) -> -46.04227 | T27: =+T25/(1.08^4) -> -42.631731 | U27: =+U25/(1.08^5) -> 824.86683
P28: =SUM(P27:U27) -> -1367.2365 | Q28: 2 puntos
B29: 5.- Inversión | C29: -2000 | E29: Inicio | G29: =+C29 -> -2000 | I29: 1 | K29: =+I29*G29 -> -2000 | M29: 3
Q30: Total = 15 puntos | W30: =SUM(W5:W21) -> 15
B35: Valor Actual de Costos | K35: =+K10+K16+K20+K27+K29+K33+K23 -> -1367.2365 | M35: =SUM(M7:M33) -> 15 | N35: puntos

Sheet Opción Chino (2)
P2: Año 0 | Q2: Año 1 | R2: Año 2 | S2: Año 3 | T2: Año 4 | U2: Año 5
E3: Años | G3: Monto de | I3: Factor de | K3: Valor Actual | O3: Flujos de Operación
E4: Flujo de Caja | G4: Flujo de Caja | I4: Descuento | K4: Flujo de Caja
I5: al 8% | O5: Costos de Mantención | Q5: -100 | R5: =+Q5 -> -100 | S5: =+R5 -> -100 | T5: =+S5 -> -100 | U5: =+T5 -> -100 | W5: 1 | X5: puntos | Z5: =+'Opción Chino (1)'!Z5 -> 2000 | AA5: =+'Opción Chino (1)'!AA5 -> Inversión
C6: 100* 85% | O6: Depreciación | Q6: =(P20*0.9)/10 -> -180 | R6: =+Q6 -> -180 | S6: =+R6 -> -180 | T6: =+S6 -> -180 | U6: =+T6 -> -180 | W6: 1 | X6: puntos | Z6: =+'Opción Chino (1)'!Z6 -> -900 | AA6: =+'Opción Chino (1)'!AA6 -> Dep Ac
Z7: =+'Opción Chino (1)'!Z7 -> 1100 | AA7: =+'Opción Chino (1)'!AA7 -> Valor libro
C8: =+'Opción Chino (1)'!C8 -> -85 | E8: del año 1 al 5 | G8: =+C8 -> -85 | I8: =+'Opción Chino (1)'!I8 -> 3.99271 | K8: =+I8*G8 -> -339.38035 | Z8: =+'Opción Chino (1)'!Z8 -> 1300 | AA8: =+'Opción Chino (1)'!AA8 -> Valor Venta
O9: UAI | Q9: =SUM(Q5:Q7) -> -280 | R9: =SUM(R5:R7) -> -280 | S9: =SUM(S5:S7) -> -280 | T9: =SUM(T5:T7) -> -280 | U9: =SUM(U5:U7) -> -280 | W9: 1 | X9: =+X6 -> puntos | Z9: =+'Opción Chino (1)'!Z9 -> 200 | AA9: =+'Opción Chino (1)'!AA9 -> Ut por Venta
B10: Total Costo Operación Variable despues de Impuestos | K10: =SUM(K8:K9) -> -339.38035 | M10: 4 | O10: Impuestos | Q10: =+Q9*0.15 -> -42 | R10: =+R9*0.15 -> -42 | S10: =+S9*0.15 -> -42 | T10: =+T9*0.15 -> -42 | U10: =+U9*0.15 -> -42 | W10: 2 | X10: =+X9 -> puntos
O11: Ut Neta | Q11: =+Q9-Q10 -> -238 | R11: =+R9-R10 -> -238 | S11: =+S9-S10 -> -238 | T11: =+T9-T10 -> -238 | U11: =+U9-U10 -> -238 | W11: 2 | X11: =+X9 -> puntos
O13: Depreciación | Q13: =+Q6 -> -180 | R13: =+R6 -> -180 | S13: =+S6 -> -180 | T13: =+T6 -> -180 | U13: =+U6 -> -180
B14: 3.- Deducciones por Depreciación Red | C14: 180
B15: 0.15 | C15: * 15%
B16: Ahorro de Impuestos por Depreciación | C16: =C14*0.15 -> 27 | E16: del año 1 al 2 | G16: =C16 -> 27 | I16: =+'Opción Chino (1)'!I16 -> 3.99271 | K16: =G16*I16 -> 107.80317 | M16: 4 | O16: Flujo Operativo | Q16: =+Q11-Q13-Q14 -> -58 | R16: =+R11-R13-R14 -> -58 | S16: =+S11-S13-S14 -> -58 | T16: =+T11-T13-T14 -> -58 | U16: =+U11-U13-U14 -> -58 | W16: 4 | X16: =+X11 -> puntos
B18: 4.- Valor de Rescate Red Actual | C18: 1270 | O18: Flujos de Inversión
B19: ( 1- 15% )
B20: Ingreso Neto de Caja | C20: =+C18 -> 1270 | E20: al año 5 | G20: =C20 -> 1270 | I20: =+'Opción Chino (1)'!I20 -> 0.6805832 | K20: =I20*G20 -> 864.34066 | M20: 4 | O20: Inversión Bus | P20: -2000 | W20: 1 | X20: puntos
O21: Venta Bus | U21: =1300-(200*0.15) -> 1270 | W21: 3 | X21: punto
O23: Flujo Inversión | P23: =+P20 -> -2000 | U23: =+U20+U21 -> 1270
O25: Flujo Total | P25: =+P16+P23 -> -2000 | Q25: =+Q16+Q23 -> -58 | R25: =+R16+R23 -> -58 | S25: =+S16+S23 -> -58 | T25: =+T16+T23 -> -58 | U25: =+U16+U23 -> 1212
O27: VP | P27: =+P25 -> -2000 | Q27: =+Q25/(1.08^1) -> -53.703704 | R27: =+R25/(1.08^2) -> -49.725652 | S27: =+S25/(1.08^3) -> -46.04227 | T27: =+T25/(1.08^4) -> -42.631731 | U27: =+U25/(1.08^5) -> 824.86683
P28: =SUM(P27:U27) -> -1367.2365 | Q28: 2 puntos
Q30: Total = 15 puntos | W30: =SUM(W5:W21) -> 15
B33: Inversión | E33: Inicio | G33: -2000 | I33: 1 | K33: -2000 | M33: 3
B35: Valor Actual de Costos | K35: =+K10+K16+K20+K27+K29+K33+K23 -> -1367.2365 | M35: =SUM(M7:M33) -> 15 | N35: puntos
K37: =+P28 -> -1367.2365
K39: =+K35-K37 -> 0

Sheet Opción Corea (1)
P2: Año 0 | Q2: Año 1 | R2: Año 2 | S2: Año 3 | T2: Año 4 | U2: Año 5
E3: Años | G3: Monto de | I3: Factor de | K3: Valor Actual | O3: Flujos de Operación
E4: Flujo de Caja | G4: Flujo de Caja | I4: Descuento | K4: Flujo de Caja
I5: al 8% | O5: Costos de Mantención | Q5: -70 | R5: =+Q5 -> -70 | S5: =+R5 -> -70 | T5: =+S5 -> -70 | U5: =+T5 -> -70 | W5: 1 | X5: puntos | Z5: =+'Opción Corea (2)'!AA6 -> 2500 | AA5: =+'Opción Corea (2)'!AB6 -> Inversión
B6: ( 1- 15% ) | C6: 70 * 85% | O6: Depreciación | Q6: =(P20*0.9)/8 -> -281.25 | R6: =+Q6 -> -281.25 | S6: =+R6 -> -281.25 | T6: =+S6 -> -281.25 | U6: =+T6 -> -281.25 | W6: 1 | X6: puntos | Z6: =+'Opción Corea (2)'!AA7 -> -1406.25 | AA6: =+'Opción Corea (2)'!AB7 -> Dep Ac
O7: Utilidad por Venta Bus | U7: =+Z9 -> -93.75 | W7: 1 | X7: puntos | Z7: =+'Opción Corea (2)'!AA8 -> 1093.75 | AA7: =+'Opción Corea (2)'!AB8 -> Valor libro
C8: =-70*0.85 -> -59.5 | E8: del año 1 al 5 | G8: =+C8 -> -59.5 | I8: =+'Opción Chino (2)'!I8 -> 3.99271 | K8: =+I8*G8 -> -237.56625 | Z8: =+'Opción Corea (2)'!AA9 -> 1000 | AA8: =+'Opción Corea (2)'!AB9 -> Valor Venta
O9: UAI | Q9: =SUM(Q5:Q7) -> -351.25 | R9: =SUM(R5:R7) -> -351.25 | S9: =SUM(S5:S7) -> -351.25 | T9: =SUM(T5:T7) -> -351.25 | U9: =SUM(U5:U7) -> -445 | W9: 2 | X9: =+X7 -> puntos | Z9: =+'Opción Corea (2)'!AA10 -> -93.75 | AA9: =+'Opción Corea (2)'!AB10 -> PP por Venta
B10: Total Costo Operación Variable despues de Impuestos | K10: =SUM(K8:K9) -> -237.56625 | M10: 3 | O10: Impuestos | Q10: =+Q9*0.15 -> -52.6875 | R10: =+R9*0.15 -> -52.6875 | S10: =+S9*0.15 -> -52.6875 | T10: =+T9*0.15 -> -52.6875 | U10: =+U9*0.15 -> -66.75 | W10: 2 | X10: =+X9 -> puntos
O11: Ut Neta | Q11: =+Q9-Q10 -> -298.5625 | R11: =+R9-R10 -> -298.5625 | S11: =+S9-S10 -> -298.5625 | T11: =+T9-T10 -> -298.5625 | U11: =+U9-U10 -> -378.25 | W11: 2 | X11: =+X9 -> puntos
O13: Depreciación | Q13: =+Q6 -> -281.25 | R13: =+R6 -> -281.25 | S13: =+S6 -> -281.25 | T13: =+T6 -> -281.25 | U13: =+U6 -> -281.25
B14: 3.- Deducciones por Depreciación Red | C14: 281.25 | O14: =+O7 -> Utilidad por Venta Bus | Q14: =+Q7 -> 0 | R14: =+R7 -> 0 | S14: =+S7 -> 0 | T14: =+T7 -> 0 | U14: =+U7 -> -93.75
B15: 0.15 | C15: * 15%
B16: Ahorro de Impuestos por Depreciación | C16: =C14*0.15 -> 42.1875 | E16: del año 1 al 5 | G16: =C16 -> 42.1875 | I16: =+I8 -> 3.99271 | K16: =G16*I16 -> 168.44245 | M16: 3 | O16: Flujo Operativo | Q16: =+Q11-Q13-Q14 -> -17.3125 | R16: =+R11-R13-R14 -> -17.3125 | S16: =+S11-S13-S14 -> -17.3125 | T16: =+T11-T13-T14 -> -17.3125 | U16: =+U11-U13-U14 -> -3.25 | W16: 4 | X16: =+X11 -> puntos
B18: 4.- Valor de Rescate Red Actual | C18: 1000 | O18: Flujos de Inversión
B19: ( 1- 15% )
B20: Ingreso Neto de Caja | C20: =+C18 -> 1000 | E20: al año 5 | G20: =C20 -> 1000 | I20: =1/(1.08^5) -> 0.6805832 | K20: =I20*G20 -> 680.5832 | M20: 3 | O20: Inversión Bus | P20: -2500 | W20: 1 | X20: puntos
O21: Venta Bus | U21: 1000 | W21: 1 | X21: punto
B22: Pérdida por Venta Máquina | C22: -93.75
C23: =-C22*0.15 -> 14.0625 | E23: al año 5 | G23: =+C23 -> 14.0625 | I23: =+I20 -> 0.6805832 | K23: =I23*G23 -> 9.5707012 | M23: 3 | O23: Flujo Inversión | P23: =+P20 -> -2500 | U23: =+U20+U21 -> 1000
O25: Flujo Total | P25: =+P16+P23 -> -2500 | Q25: =+Q16+Q23 -> -17.3125 | R25: =+R16+R23 -> -17.3125 | S25: =+S16+S23 -> -17.3125 | T25: =+T16+T23 -> -17.3125 | U25: =+U16+U23 -> 996.75
O27: VP | P27: =+P25 -> -2500 | Q27: =+Q25/(1.08^1) -> -16.030093 | R27: =+R25/(1.08^2) -> -14.842678 | S27: =+S25/(1.08^3) -> -13.743221 | T27: =+T25/(1.08^4) -> -12.725204 | U27: =+U25/(1.08^5) -> 678.3713
P28: =SUM(P27:U27) -> -1878.9699 | Q28: 2 puntos
B29: 5.- Inversión | C29: -2500 | E29: Inicio | G29: =+C29 -> -2500 | I29: 1 | K29: =+I29*G29 -> -2500 | M29: 3
Q30: Total = 15 puntos | W30: =SUM(W5:W21) -> 15
B35: Valor Actual de Costos | K35: =+K10+K16+K20+K27+K29+K33+K23 -> -1878.9699 | M35: =SUM(M7:M33) -> 15 | N35: puntos

Sheet Opción Corea (2)
P2: Año 0 | Q2: Año 1 | R2: Año 2 | S2: Año 3 | T2: Año 4 | U2: Año 5
E3: Años | G3: Monto de | I3: Factor de | K3: Valor Actual | O3: Flujos de Operación
E4: Flujo de Caja | G4: Flujo de Caja | I4: Descuento | K4: Flujo de Caja
I5: al 8% | O5: Costos de Mantención | Q5: -70 | R5: =+Q5 -> -70 | S5: =+R5 -> -70 | T5: =+S5 -> -70 | U5: =+T5 -> -70 | W5: 1 | X5: puntos
B6: ( 1- 15% ) | C6: 70 * 85% | O6: Depreciación | Q6: =(P20*0.9)/8 -> -281.25 | R6: =+Q6 -> -281.25 | S6: =+R6 -> -281.25 | T6: =+S6 -> -281.25 | U6: =+T6 -> -281.25 | W6: 1 | X6: puntos | AA6: =-P20 -> 2500 | AB6: Inversión
O7: Utilidad por Venta Bus | AA7: =SUM(Q6:U6) -> -1406.25 | AB7: Dep Ac
C8: =-70*0.85 -> -59.5 | E8: del año 1 al 5 | G8: =+C8 -> -59.5 | I8: =+'Opción Corea (1)'!I8 -> 3.99271 | K8: =+I8*G8 -> -237.56625 | AA8: =+AA6+AA7 -> 1093.75 | AB8: Valor libro
O9: UAI | Q9: =SUM(Q5:Q7) -> -351.25 | R9: =SUM(R5:R7) -> -351.25 | S9: =SUM(S5:S7) -> -351.25 | T9: =SUM(T5:T7) -> -351.25 | U9: =SUM(U5:U7) -> -351.25 | W9: 1 | X9: =+X6 -> puntos | AA9: 1000 | AB9: Valor Venta
B10: Total Costo Operación Variable despues de Impuestos | K10: =SUM(K8:K9) -> -237.56625 | M10: 4 | O10: Impuestos | Q10: =+Q9*0.15 -> -52.6875 | R10: =+R9*0.15 -> -52.6875 | S10: =+S9*0.15 -> -52.6875 | T10: =+T9*0.15 -> -52.6875 | U10: =+U9*0.15 -> -52.6875 | W10: 2 | X10: =+X9 -> puntos | AA10: =+AA9-AA8 -> -93.75 | AB10: PP por Venta
O11: Ut Neta | Q11: =+Q9-Q10 -> -298.5625 | R11: =+R9-R10 -> -298.5625 | S11: =+S9-S10 -> -298.5625 | T11: =+T9-T10 -> -298.5625 | U11: =+U9-U10 -> -298.5625 | W11: 2 | X11: =+X9 -> puntos
O13: Depreciación | Q13: =+Q6 -> -281.25 | R13: =+R6 -> -281.25 | S13: =+S6 -> -281.25 | T13: =+T6 -> -281.25 | U13: =+U6 -> -281.25
B14: 3.- Deducciones por Depreciación Red | C14: 281.25 | O14: =+O7 -> Utilidad por Venta Bus | Q14: =+Q7 -> 0 | R14: =+R7 -> 0 | S14: =+S7 -> 0 | T14: =+T7 -> 0 | U14: =+U7 -> 0
B15: 0.15 | C15: * 15%
B16: Ahorro de Impuestos por Depreciación | C16: =C14*0.15 -> 42.1875 | E16: del año 1 al 5 | G16: =C16 -> 42.1875 | I16: =+'Opción Corea (1)'!I16 -> 3.99271 | K16: =G16*I16 -> 168.44245 | M16: 4 | O16: Flujo Operativo | Q16: =+Q11-Q13-Q14 -> -17.3125 | R16: =+R11-R13-R14 -> -17.3125 | S16: =+S11-S13-S14 -> -17.3125 | T16: =+T11-T13-T14 -> -17.3125 | U16: =+U11-U13-U14 -> -17.3125 | W16: 4 | X16: =+X11 -> puntos
B18: 4.- Valor de Rescate Red Actual | C18: =1000+14.06 -> 1014.06 | O18: Flujos de Inversión
B19: ( 1- 15% )
B20: Ingreso Neto de Caja | C20: =+C18 -> 1014.06 | E20: al año 5 | G20: =C20 -> 1014.06 | I20: =+'Opción Corea (1)'!I20 -> 0.6805832 | K20: =I20*G20 -> 690.1522 | M20: 4 | O20: Inversión Bus | P20: -2500 | W20: 1 | X20: puntos
O21: Venta Bus | U21: =1000+(-AA10*0.15) -> 1014.0625 | W21: 3 | X21: punto
O23: Flujo Inversión | P23: =+P20 -> -2500 | U23: =+U20+U21 -> 1014.0625
O25: Flujo Total | P25: =+P16+P23 -> -2500 | Q25: =+Q16+Q23 -> -17.3125 | R25: =+R16+R23 -> -17.3125 | S25: =+S16+S23 -> -17.3125 | T25: =+T16+T23 -> -17.3125 | U25: =+U16+U23 -> 996.75
O27: VP | P27: =+P25 -> -2500 | Q27: =+Q25/(1.08^1) -> -16.030093 | R27: =+R25/(1.08^2) -> -14.842678 | S27: =+S25/(1.08^3) -> -13.743221 | T27: =+T25/(1.08^4) -> -12.725204 | U27: =+U25/(1.08^5) -> 678.3713
P28: =SUM(P27:U27) -> -1878.9699 | Q28: 2 puntos
B29: 5.- Inversión | C29: -2500 | E29: Inicio | G29: =+C29 -> -2500 | I29: 1 | K29: =+I29*G29 -> -2500 | M29: 3
Q30: Total = 15 puntos | V30: =SUM(W5:W21) -> 15
B35: Valor Actual de Costos | K35: =+K10+K16+K20+K27+K29+K33+K23 -> -1878.9716 | M35: =SUM(M7:M33) -> 15 | N35: puntos
K37: =+P28 -> -1878.9699
K39: =+K35-K37 -> -0.001701458
